{
  "tasks": [
    {
      "id": "1",
      "title": "Mechanical Keyboard Kit",
      "description": "Cost: $120. Custom 75% build layout profile.",
      "priority": "low",
      "status": "pending",
      "dueDate": "2026-06-15"
    },
    {
      "id": "2",
      "title": "Monthly Cloud Server Hosting Fee",
      "description": "Cost: $15. Essential operational infrastructure billing.",
      "priority": "high",
      "status": "done",
      "dueDate": "2026-06-01"
    },
    {
      "id": "3",
      "title": "Weekly Grocery Restock",
      "description": "Cost: $65. Standard meal preparation ingredients.",
      "priority": "medium",
      "status": "in-progress",
      "dueDate": "2026-06-08"
    }
  ],
  "users": [
    {
      "id": "tester",
      "password": "password"
    }
  ],
  "transactions": [
    {
      "id": "1780631602307",
      "date": "2026-06-05",
      "description": "Test Offline Sync Item",
      "category": "Food & Dining",
      "type": "expense",
      "amount": 99.99,
      "userId": "tester"
    }
  ],
  "bills": [],
  "wants": []
}